rpmspectool/__init__.py
rpmspectool/cli.py
rpmspectool/download.py
rpmspectool/rpm.py
rpmspectool/version.py
rpmspectool-1.99.10.dist-info/COPYING
rpmspectool-1.99.10.dist-info/METADATA
rpmspectool-1.99.10.dist-info/WHEEL
rpmspectool-1.99.10.dist-info/entry_points.txt
rpmspectool-1.99.10.dist-info/RECORD
